ConfigByLmdb/DB.py
ConfigByLmdb/__init__.py
ConfigByLmdb/web.py
ConfigByLmdb/Test/__init__.py
ConfigByLmdb/Test/demo.py
ConfigByLmdb-0.0.10.dist-info/LICENSE
ConfigByLmdb-0.0.10.dist-info/METADATA
ConfigByLmdb-0.0.10.dist-info/WHEEL
ConfigByLmdb-0.0.10.dist-info/top_level.txt
ConfigByLmdb-0.0.10.dist-info/RECORD
