Metadata-Version: 2.1
Name: ConfigByLmdb
Version: 0.0.10
Summary: lmdb 自定义封装
Home-page: https://github.com/jnwatson/py-lmdb/
Author: CC
Author-email: 3204604858@qq.com
License: The OpenLDAP Public License
Keywords: ConfigByLmdb,ConfigDB,lmdb
Platform: Windows
Classifier: Intended Audience :: Developers
Classifier: Programming Language :: Python :: 3.7
Classifier: Programming Language :: Python :: 3.8
Classifier: Programming Language :: Python :: 3.9
Classifier: Programming Language :: Python :: 3.10
Classifier: Programming Language :: Python :: 3.11
Classifier: Programming Language :: Python :: 3.12
Classifier: Topic :: Software Development :: Libraries
Classifier: Topic :: Software Development :: Libraries :: Python Modules
Classifier: Topic :: Software Development :: User Interfaces
Requires-Python: >=3
License-File: LICENSE
Requires-Dist: lmdb
Requires-Dist: fastapi
